postdoc.py
postdoc-1.0.0.dist-info/DESCRIPTION.rst
postdoc-1.0.0.dist-info/METADATA
postdoc-1.0.0.dist-info/RECORD
postdoc-1.0.0.dist-info/WHEEL
postdoc-1.0.0.dist-info/entry_points.txt
postdoc-1.0.0.dist-info/metadata.json
postdoc-1.0.0.dist-info/top_level.txt
