Metadata-Version: 2.0
Name: postdoc
Version: 1.0.0
Summary: A helper for Postgres + Docker that works for free
Home-page: https://github.com/crccheck/postdoc
Author: Chris Chang
Author-email: c@crccheck.com
License: Apache
Platform: UNKNOWN
Classifier: Development Status :: 4 - Beta
Classifier: Environment :: Console
Classifier: License :: OSI Approved :: Apache Software License
Classifier: Programming Language :: Python
Classifier: Programming Language :: Python :: 2
Classifier: Programming Language :: Python :: 3
Classifier: Topic :: Database
Classifier: Topic :: Utilities
